scdiff/ClusteringMetric.py
scdiff/Distance.py
scdiff/File.py
scdiff/KF2.py
scdiff/StatTest.py
scdiff/__init__.py
scdiff/scdiff.py
scdiff/scdiff_gui.py
scdiff/viz.py
scdiff/img/logo.gif
scdiff/tfdata/HumanTFList.txt
scdiff-1.1.16.dist-info/DESCRIPTION.rst
scdiff-1.1.16.dist-info/METADATA
scdiff-1.1.16.dist-info/RECORD
scdiff-1.1.16.dist-info/WHEEL
scdiff-1.1.16.dist-info/entry_points.txt
scdiff-1.1.16.dist-info/metadata.json
scdiff-1.1.16.dist-info/top_level.txt
