Metadata-Version: 2.0
Name: scdiff
Version: 1.1.16
Summary: Single Cell Differentiation Model package
Home-page: https://github.com/phoenixding/scdiff
Author: Jun Ding
Author-email: jund@andrew.cmu.edu
License: MIT
Platform: UNKNOWN
Classifier: License :: OSI Approved :: MIT License
Classifier: Programming Language :: Python :: 2
Classifier: Programming Language :: Python :: 3
Requires-Dist: scipy (>0.13.3)
Requires-Dist: numpy (>1.8.2)
Requires-Dist: scikit-learn (>=0.20)
Requires-Dist: cloudpickle (<0.6,>0.5)
Requires-Dist: pydiffmap
Requires-Dist: matplotlib (<3.0)
Requires-Dist: imbalanced-learn
